Metadata-Version: 1.0
Name: cmr05-distributions
Version: 0.1
Summary: Gaussian and Binomial distributions
Home-page: UNKNOWN
Author: Christian Relling
Author-email: mail@relling.com
License: UNKNOWN
Platform: UNKNOWN
